LICENSE
README.md
setup.py
src/npm_analyser/__init__.py
src/npm_analyser/npm_analyser.py
src/npm_analyser_withrepo.egg-info/PKG-INFO
src/npm_analyser_withrepo.egg-info/SOURCES.txt
src/npm_analyser_withrepo.egg-info/dependency_links.txt
src/npm_analyser_withrepo.egg-info/top_level.txt