Metadata-Version: 2.1
Name: npm-analyser-withrepo
Version: 1.0.0
Summary: A Python library to monitor an npm package!
Home-page: https://github.com/alexcote1/npm_analyser
Author: alex cote
Project-URL: Bug Tracker, https://github.com/alexcote1/npm_analyser/issues
Classifier: Programming Language :: Python :: 3
Classifier: License :: OSI Approved :: MIT License
Requires-Python: >=3.9.7
License-File: LICENSE
